zibanu/django/auth/__init__.py
zibanu/django/auth/admin.py
zibanu/django/auth/admin_views.py
zibanu/django/auth/apps.py
zibanu/django/auth/models.py
zibanu/django/auth/urls.py
zibanu/django/auth/api/__init__.py
zibanu/django/auth/api/serializers/__init__.py
zibanu/django/auth/api/serializers/group.py
zibanu/django/auth/api/serializers/permission.py
zibanu/django/auth/api/serializers/profile.py
zibanu/django/auth/api/serializers/token.py
zibanu/django/auth/api/serializers/user.py
zibanu/django/auth/api/services/__init__.py
zibanu/django/auth/api/services/auth.py
zibanu/django/auth/api/services/group.py
zibanu/django/auth/api/services/group_level.py
zibanu/django/auth/api/services/permission.py
zibanu/django/auth/api/services/profile.py
zibanu/django/auth/api/services/user.py
zibanu/django/auth/lib/__init__.py
zibanu/django/auth/lib/backends.py
zibanu/django/auth/lib/enums.py
zibanu/django/auth/lib/receivers.py
zibanu/django/auth/lib/signals.py
zibanu/django/auth/lib/utils.py
zibanu/django/auth/locale/es/LC_MESSAGES/django.mo
zibanu/django/auth/locale/es/LC_MESSAGES/django.po
zibanu/django/auth/migrations/0001_initial.py
zibanu/django/auth/migrations/0002_alter_userprofile_timezone.py
zibanu/django/auth/migrations/0003_userprofile_multiple_login.py
zibanu/django/auth/migrations/0004_userprofile_secure_password.py
zibanu/django/auth/migrations/0005_alter_userprofile_avatar.py
zibanu/django/auth/migrations/0006_alter_userprofile_app_profile_and_more.py
zibanu/django/auth/migrations/0007_grouplevel.py
zibanu/django/auth/migrations/0008_alter_grouplevel_level.py
zibanu/django/auth/migrations/0009_user.py
zibanu/django/auth/migrations/0010_rename_app_profile_userprofile_app_settings.py
zibanu/django/auth/migrations/0011_alter_userprofile_theme.py
zibanu/django/auth/migrations/0012_alter_userprofile_options.py
zibanu/django/auth/migrations/0013_alter_userprofile_timezone.py
zibanu/django/auth/migrations/__init__.py
zibanu/django/auth/templates/change_password.html
zibanu_django_auth-1.2.7.dist-info/licenses/LICENSE
zibanu_django_auth-1.2.7.dist-info/METADATA
zibanu_django_auth-1.2.7.dist-info/WHEEL
zibanu_django_auth-1.2.7.dist-info/top_level.txt
zibanu_django_auth-1.2.7.dist-info/RECORD
