Metadata-Version: 2.4
Name: zibanu-django-auth
Version: 1.2.7
Summary: Zibanu authentication library for django projects
Author-email: Mario Cerón <mario.ceron@cqinversiones.co>
License-Expression: GPL-3.0-or-later
Keywords: django,zibanu,library
Classifier: Programming Language :: Python :: 3.9
Classifier: Programming Language :: Python :: 3.11
Classifier: Development Status :: 3 - Alpha
Classifier: Framework :: Django
Classifier: Framework :: Django :: 4.1
Classifier: Environment :: Web Environment
Classifier: Operating System :: OS Independent
Classifier: Topic :: Internet :: WWW/HTTP
Requires-Python: >=3.9
License-File: LICENSE
Requires-Dist: Django>=4.1
Requires-Dist: djangorestframework
Requires-Dist: django-timezone-utils
Requires-Dist: djangorestframework-simplejwt
Requires-Dist: zibanu-django>=1.5.0
Dynamic: license-file
